DMLP/__init__.py
DMLP/models/__init__.py
DMLP/models/abstract_models.py
DMLP/models/log_sum_exp.py
DMLP/models/models.py
DMLP/models/my_transformers.py
DMLP/train/__init__.py
DMLP/train/evaluation.py
DMLP/train/generation.py
DMLP/train/reconstruction.py
DMLP/train/train_function.py
DMLP/utils/__init__.py
DMLP/utils/ddpm_schedule.py
DMLP/utils/random_init.py
DMLP/utils/sample.py
DMLP/utils/save_checkpoint.py
DMLP-1.0.0.dist-info/LICENSE.txt
DMLP-1.0.0.dist-info/METADATA
DMLP-1.0.0.dist-info/WHEEL
DMLP-1.0.0.dist-info/top_level.txt
DMLP-1.0.0.dist-info/RECORD
