Metadata-Version: 2.1
Name: DMLP
Version: 1.0.0
Summary: My first Python package
Home-page: UNKNOWN
Author: YunhaoLi, Jieqi Liu
Author-email: <youremail@email.com>
License: UNKNOWN
Keywords: python,first package
Platform: UNKNOWN
Classifier: Development Status :: 3 - Alpha
Classifier: Intended Audience :: Education
Classifier: Programming Language :: Python :: 2
Classifier: Programming Language :: Python :: 3
Classifier: Operating System :: MacOS :: MacOS X
Classifier: Operating System :: Microsoft :: Windows
License-File: LICENSE.txt
